qiwi_payments/__init__.py
qiwi_payments/constants.py
qiwi_payments/kassa.py
qiwi_payments/models.py
qiwi_payments/utils.py
qiwi_payments/wallet.py
qiwi_payments-0.1.dist-info/LICENSE
qiwi_payments-0.1.dist-info/METADATA
qiwi_payments-0.1.dist-info/WHEEL
qiwi_payments-0.1.dist-info/top_level.txt
qiwi_payments-0.1.dist-info/RECORD
